nefertem_validation/__init__.py
nefertem_validation/utils.py
nefertem_validation/metadata/__init__.py
nefertem_validation/metadata/report.py
nefertem_validation/plugins/builder.py
nefertem_validation/plugins/constraint.py
nefertem_validation/plugins/plugin.py
nefertem_validation/plugins/utils.py
nefertem_validation/run/__init__.py
nefertem_validation/run/run.py
nefertem_validation-2.0.2.dist-info/LICENSE.txt
nefertem_validation-2.0.2.dist-info/METADATA
nefertem_validation-2.0.2.dist-info/WHEEL
nefertem_validation-2.0.2.dist-info/top_level.txt
nefertem_validation-2.0.2.dist-info/RECORD
